poocr/__init__.py
poocr/api/__init__.py
poocr/api/ocr.py
poocr/api/ocr2excel.py
poocr/core/BaiduOCR.py
poocr/core/HuaweiOCR.py
poocr/core/OCR.py
poocr/core/OfdOCR.py
poocr/core/__init__.py
poocr/lib/CommonUtils.py
poocr/lib/Config.py
poocr/lib/Const.py
poocr/lib/__init__.py
poocr/lib/apig_sdk/__init__.py
poocr/lib/apig_sdk/signer.py
tests/__init__.py
tests/test_code/__init__.py
tests/test_code/test_dev.py
tests/test_code/test_huawei.py
tests/test_code/test_ocr2excel.py
poali-0.0.1.dist-info/LICENSE
poali-0.0.1.dist-info/METADATA
poali-0.0.1.dist-info/WHEEL
poali-0.0.1.dist-info/top_level.txt
poali-0.0.1.dist-info/RECORD
