Metadata-Version: 2.1
Name: poali
Version: 0.0.1
Summary: pip install poali
Home-page: https://www.python-office.com/
Author: CoderWanFeng
Author-email: 1957875073@qq.com
License: MIT
Project-URL: Bug Tracker, https://github.com/CoderWanFeng/poali/issues
Project-URL: Documentation, https://github.com/CoderWanFeng/poali/blob/main/README.md
Project-URL: Source Code, https://github.com/CoderWanFeng/poali
Platform: any
Requires-Python: >=3.7
License-File: LICENSE
Requires-Dist: toml
Requires-Dist: potx-cloud
Requires-Dist: pofile
Requires-Dist: pandas
Requires-Dist: poprogress
Requires-Dist: loguru
Requires-Dist: PyMuPDF
Requires-Dist: tencentcloud-sdk-python
Requires-Dist: huaweicloudsdkocr
Requires-Dist: huaweicloudsdkcore
